yews/__init__.py
yews/cpic/__init__.py
yews/cpic/detection.py
yews/cpic/picking.py
yews/cpic/utils.py
yews/datasets/__init__.py
yews/datasets/base.py
yews/datasets/packaged_datasets.py
yews/datasets/sac.py
yews/datasets/utils.py
yews/models/__init__.py
yews/models/cpic.py
yews/models/utils.py
yews/train/__init__.py
yews/train/functional.py
yews/train/train.py
yews/train/utils.py
yews/transforms/__init__.py
yews/transforms/base.py
yews/transforms/functional.py
yews/transforms/transforms.py
yews-0.0.6.dist-info/LICENSE
yews-0.0.6.dist-info/METADATA
yews-0.0.6.dist-info/WHEEL
yews-0.0.6.dist-info/top_level.txt
yews-0.0.6.dist-info/zip-safe
yews-0.0.6.dist-info/RECORD
