Metadata-Version: 2.1
Name: yews
Version: 0.0.6
Summary: Deep Learning toolbox for seismic waveform processing.
Home-page: https://github.com/lijunzh/yews
Author: Lijun Zhu
Author-email: gatechzhu@gmail.com
License: Apache 2.0
Project-URL: Documentation, https://yews.info/
Platform: any
Classifier: Development Status :: 2 - Pre-Alpha
Classifier: Topic :: Scientific/Engineering
Classifier: Topic :: Scientific/Engineering :: Artificial Intelligence
Classifier: Topic :: Scientific/Engineering :: Physics
Classifier: Programming Language :: Python
Classifier: Programming Language :: Python :: 3
Classifier: Programming Language :: Python :: 3 :: Only
Classifier: Programming Language :: Python :: 3.6
Classifier: Programming Language :: Python :: 3.7
Classifier: Environment :: Console
Classifier: Intended Audience :: Developers
Classifier: Intended Audience :: Science/Research
Classifier: License :: OSI Approved :: Apache Software License
Classifier: Operating System :: POSIX :: Linux
Classifier: Operating System :: Unix
Classifier: Operating System :: MacOS
Classifier: Operating System :: Microsoft :: Windows
Requires-Python: >=3.6
Requires-Dist: numpy (>=1.16)
Requires-Dist: scipy (>=1.2)
Requires-Dist: torch (>=1.0)
Provides-Extra: all
Requires-Dist: obspy ; extra == 'all'
Requires-Dist: tqdm ; extra == 'all'
Provides-Extra: testing
Requires-Dist: pytest ; extra == 'testing'
Requires-Dist: pytest-cov ; extra == 'testing'
Requires-Dist: obspy ; extra == 'testing'
